[
  {"imgSrc":"images/songMenu9.jpg","title":"【日系】献给曾经那个...","name":"Armin6"},
  {"imgSrc":"images/songMenu10.jpg","title":"香港电影中的50首经典...","name":"寺诗_"},
  {"imgSrc":"images/songMenu11.jpg","title":"与自由并行聆听清新...","name":"肥啊肥肉"},
  {"imgSrc":"images/songMenu12.jpg","title":"时光汹涌，愿你是时光...","name":"Lynko"},
  {"imgSrc":"images/songMenu13.jpg","title":"八月如期而至，给我...","name":"阿杰Ajay"},
  {"imgSrc":"images/songMenu14.jpg","title":"『ACG』经典ACG的交响翻奏...","name":"七香"},
  {"imgSrc":"images/songMenu1.jpg","title":"『狂躁电子』Hards...","name":"目隐子行"},
  {"imgSrc":"images/songMenu2.jpg","title":"七月最IN电子音乐推荐...","name":"巫女密簿"},
  {"imgSrc":"images/songMenu3.jpg","title":"与自由并行聆听清新...","name":"by W-A-A"},
  {"imgSrc":"images/songMenu4.jpg","title":"时光汹涌，愿你是时光...","name":"by 左耳右耳不一样"},
  {"imgSrc":"images/songMenu5.jpg","title":"八月如期而至，给我...","name":"by 这条平凡的狗"},
  {"imgSrc":"images/songMenu6.jpg","title":"『ACG』经典ACG的交响翻奏...","name":"by DoubleRainbow_ "},
  {"imgSrc":"images/songMenu7.jpg","title":"『狂躁电子』Hards...","name":"y 男票是茶蛋的棕棕"},
  {"imgSrc":"images/songMenu8.jpg","title":"七月最IN电子音乐推荐...","name":"王飞机_"},
  {"imgSrc":"images/songMenu9.jpg","title":"【日系】献给曾经那个...","name":"Armin6"},
  {"imgSrc":"images/songMenu10.jpg","title":"香港电影中的50首经典...","name":"寺诗_"},
  {"imgSrc":"images/songMenu11.jpg","title":"与自由并行聆听清新...","name":"肥啊肥肉"},
  {"imgSrc":"images/songMenu12.jpg","title":"时光汹涌，愿你是时光...","name":"Lynko"},
  {"imgSrc":"images/songMenu13.jpg","title":"八月如期而至，给我...","name":"阿杰Ajay"},
  {"imgSrc":"images/songMenu14.jpg","title":"『ACG』经典ACG的交响翻奏...","name":"七香"},
  {"imgSrc":"images/songMenu1.jpg","title":"『狂躁电子』Hards...","name":"目隐子行"},
  {"imgSrc":"images/songMenu2.jpg","title":"七月最IN电子音乐推荐...","name":"巫女密簿"},
  {"imgSrc":"images/songMenu3.jpg","title":"与自由并行聆听清新...","name":"by W-A-A"},
  {"imgSrc":"images/songMenu4.jpg","title":"时光汹涌，愿你是时光...","name":"by 左耳右耳不一样"},
  {"imgSrc":"images/songMenu5.jpg","title":"八月如期而至，给我...","name":"by 这条平凡的狗"},
  {"imgSrc":"images/songMenu6.jpg","title":"『ACG』经典ACG的交响翻奏...","name":"by DoubleRainbow_ "},
  {"imgSrc":"images/songMenu7.jpg","title":"『狂躁电子』Hards...","name":"y 男票是茶蛋的棕棕"},
  {"imgSrc":"images/songMenu8.jpg","title":"七月最IN电子音乐推荐...","name":"王飞机_"}
]